setup.py
orakwlum/__init__.py
orakwlum.egg-info/PKG-INFO
orakwlum.egg-info/SOURCES.txt
orakwlum.egg-info/dependency_links.txt
orakwlum.egg-info/requires.txt
orakwlum.egg-info/top_level.txt
orakwlum/importer/F1.py
orakwlum/importer/F5D.py
orakwlum/importer/__init__.py
orakwlum/importer/importer.py
orakwlum/importer/static_data.py
orakwlum/input/__init__.py
orakwlum/input/file.py
orakwlum/input/input.py
orakwlum/input/message.py
orakwlum/queuer/__init__.py
orakwlum/queuer/queue.py
orakwlum/queuer/redis.py
orakwlum/worker/F1.py
orakwlum/worker/F5D.py
orakwlum/worker/__init__.py
orakwlum/worker/static_data.py
orakwlum/worker/worker.py